llama_index/vector_stores/db2/__init__.py
llama_index/vector_stores/db2/base.py
llama_index_vector_stores_db2-0.1.0.dist-info/METADATA
llama_index_vector_stores_db2-0.1.0.dist-info/WHEEL
llama_index_vector_stores_db2-0.1.0.dist-info/licenses/LICENSE
llama_index_vector_stores_db2-0.1.0.dist-info/RECORD
