Metadata-Version: 2.4
Name: llama-index-vector-stores-db2
Version: 0.1.0
Summary: llama-index vector_stores db2 database integration
Author-email: Your Name <you@example.com>
License-Expression: MIT
License-File: LICENSE
Requires-Python: <3.13,>=3.9
Requires-Dist: ibm-db>=3.2.6
Requires-Dist: llama-index-core<0.13,>=0.12.0
